holidata/__init__.py
holidata/emitters.py
holidata/holiday.py
holidata/plugin.py
holidata/utils.py
holidata/holidays/__init__.py
holidata/holidays/AT/__init__.py
holidata/holidays/AU/ACT.py
holidata/holidays/AU/NSW.py
holidata/holidays/AU/NT.py
holidata/holidays/AU/QLD.py
holidata/holidays/AU/SA.py
holidata/holidays/AU/TAS.py
holidata/holidays/AU/VIC.py
holidata/holidays/AU/WA.py
holidata/holidays/AU/__init__.py
holidata/holidays/BE/__init__.py
holidata/holidays/BR/__init__.py
holidata/holidays/CA/__init__.py
holidata/holidays/CH/__init__.py
holidata/holidays/CO/__init__.py
holidata/holidays/CZ/__init__.py
holidata/holidays/DE/BB.py
holidata/holidays/DE/BE.py
holidata/holidays/DE/BW.py
holidata/holidays/DE/BY.py
holidata/holidays/DE/HB.py
holidata/holidays/DE/HE.py
holidata/holidays/DE/HH.py
holidata/holidays/DE/MV.py
holidata/holidays/DE/NI.py
holidata/holidays/DE/NW.py
holidata/holidays/DE/RP.py
holidata/holidays/DE/SH.py
holidata/holidays/DE/SL.py
holidata/holidays/DE/SN.py
holidata/holidays/DE/ST.py
holidata/holidays/DE/TH.py
holidata/holidays/DE/__init__.py
holidata/holidays/DK/__init__.py
holidata/holidays/EE/__init__.py
holidata/holidays/ES/AN.py
holidata/holidays/ES/AR.py
holidata/holidays/ES/AS.py
holidata/holidays/ES/CB.py
holidata/holidays/ES/CE.py
holidata/holidays/ES/CL.py
holidata/holidays/ES/CM.py
holidata/holidays/ES/CN.py
holidata/holidays/ES/CT.py
holidata/holidays/ES/EX.py
holidata/holidays/ES/GA.py
holidata/holidays/ES/IB.py
holidata/holidays/ES/MC.py
holidata/holidays/ES/MD.py
holidata/holidays/ES/ML.py
holidata/holidays/ES/NC.py
holidata/holidays/ES/PV.py
holidata/holidays/ES/RI.py
holidata/holidays/ES/VC.py
holidata/holidays/ES/__init__.py
holidata/holidays/FI/__init__.py
holidata/holidays/FR/__init__.py
holidata/holidays/GB/__init__.py
holidata/holidays/GR/__init__.py
holidata/holidays/HR/__init__.py
holidata/holidays/HU/__init__.py
holidata/holidays/IS/__init__.py
holidata/holidays/IT/__init__.py
holidata/holidays/LU/__init__.py
holidata-2026.1.2.dist-info/licenses/LICENSE
holidata-2026.1.2.dist-info/METADATA
holidata-2026.1.2.dist-info/WHEEL
holidata-2026.1.2.dist-info/top_level.txt
holidata-2026.1.2.dist-info/RECORD
