Metadata-Version: 2.4
Name: holidata
Version: 2026.1.2
Summary: Holidata is a utility for algorithmically producing holidays for a given locale and year
Home-page: https://github.com/GothenburgBitFactory/holidata
Author: Gothenburg Bit Factory
Author-email: support@gothenburgbitfactory.org
Project-URL: Bug Reports, https://github.com/GothenburgBitFactory/holidata/issues
Project-URL: Source, https://github.com/GothenburgBitFactory/holidata
Project-URL: Website, https://holidata.net
Keywords: holiday,calendar
Classifier: Development Status :: 5 - Production/Stable
Classifier: License :: OSI Approved :: MIT License
Classifier: Programming Language :: Python :: 3
Classifier: Programming Language :: Python :: 3.10
Classifier: Programming Language :: Python :: 3.11
Classifier: Programming Language :: Python :: 3.12
Classifier: Programming Language :: Python :: 3.13
Classifier: Programming Language :: Python :: 3 :: Only
Requires-Python: >=3.10, <4
License-File: LICENSE
Requires-Dist: arrow>=1.4.0
Requires-Dist: docopt>=0.6.2
Provides-Extra: test
Requires-Dist: pytest>=9.0.2; extra == "test"
Requires-Dist: syrupy>=5.0.0; extra == "test"
Dynamic: author
Dynamic: author-email
Dynamic: classifier
Dynamic: description
Dynamic: description-content-type
Dynamic: home-page
Dynamic: keywords
Dynamic: license-file
Dynamic: project-url
Dynamic: provides-extra
Dynamic: requires-dist
Dynamic: requires-python
Dynamic: summary
